restapi/__init__.py
restapi/api.py
restapi/error.py
restapi/http.py
restapi/node.py
restapi/request.py
restapi/response.py
restapi/utils.py
restapi/wsgi.py
restapi_wsgi-0.0.1.dist-info/LICENSE
restapi_wsgi-0.0.1.dist-info/METADATA
restapi_wsgi-0.0.1.dist-info/WHEEL
restapi_wsgi-0.0.1.dist-info/top_level.txt
restapi_wsgi-0.0.1.dist-info/RECORD
