Metadata-Version: 2.1
Name: restapi-wsgi
Version: 0.0.1
Summary: A lightweight WSGI REST API framework
Home-page: https://github.com/charlestolley/restapi-wsgi
Author: Charles Tolley
Author-email: charlestolley@gmail.com
License: GPLv3+
Platform: UNKNOWN
Classifier: Development Status :: 3 - Alpha
Classifier: Intended Audience :: Developers
Classifier: License :: OSI Approved :: GNU General Public License v3 or later (GPLv3+)
Classifier: Natural Language :: English
Classifier: Programming Language :: Python :: 3 :: Only
Classifier: Topic :: Internet :: WWW/HTTP :: WSGI :: Application
Classifier: Topic :: Software Development :: Libraries :: Application Frameworks
Requires-Python: <4,>=3
